{
  "name": "Highpower A Grade 3.2V 100Ah Laser LiFePO4 Cell",
  "category": "LFP",
  "description": "A-grade 100Ah prismatic LiFePO4 cell for laser-welded pack builds and storage systems.",
  "image": "/uploads/product-images/highpower-100ah-laser.jpg",
  "voltage": "3.2V",
  "capacity": "100Ah",
  "price": "Contact for quote",
  "stockStatus": "In Stock",
  "sortOrder": 10,
  "specifications": [
    {
      "label": "Terminal",
      "value": "Laser"
    },
    {
      "label": "Voltage",
      "value": "3.2V"
    },
    {
      "label": "Capacity",
      "value": "100Ah"
    }
  ]
}
