{
  "name": "TENPOWER 18650-26ME Li-Ion Cell",
  "category": "NCM",
  "description": "TENPOWER 18650 lithium-ion cell for high-current battery pack requirements.",
  "image": "/uploads/product-images/tenpower-18650-26me.jpg",
  "voltage": "3.7V",
  "capacity": "2600mAh",
  "price": "Contact for quote",
  "stockStatus": "In Stock",
  "sortOrder": 4,
  "specifications": [
    {
      "label": "Model",
      "value": "18650-26ME"
    },
    {
      "label": "Voltage",
      "value": "3.7V"
    },
    {
      "label": "Capacity",
      "value": "2600mAh"
    }
  ]
}
